mlx_tuning_fork/__init__.py
mlx_tuning_fork/config.py
mlx_tuning_fork/dataset.py
mlx_tuning_fork/generate.py
mlx_tuning_fork/reporting.py
mlx_tuning_fork/training.py
mlx_tuning_fork/wandb_sweep.py
mlx_tuning_fork/prompt_templates/__init__.py
mlx_tuning_fork/prompt_templates/alpaca.py
mlx_tuning_fork/prompt_templates/chatml.py
mlx_tuning_fork/prompt_templates/gemma.py
mlx_tuning_fork/prompt_templates/llama3.py
mlx_tuning_fork/prompt_templates/mistral.py
mlx_tuning_fork/prompt_templates/phi.py
mlx_tuning_fork/tuning/__init__.py
mlx_tuning_fork/tuning/input_masking.py
mlx_tuning_fork/tuning/utils.py
mlx_tuning_fork-0.4.0.dist-info/LICENSE
mlx_tuning_fork-0.4.0.dist-info/METADATA
mlx_tuning_fork-0.4.0.dist-info/WHEEL
mlx_tuning_fork-0.4.0.dist-info/entry_points.txt
mlx_tuning_fork-0.4.0.dist-info/top_level.txt
mlx_tuning_fork-0.4.0.dist-info/RECORD
