Metadata-Version: 2.2
Name: mlx-tuning-fork
Version: 0.4.0
Summary: Basic framework for LLM (Q)LoRA fine-tuning using mlx, mlx_lm, and OgbujiPT.
Author-email: Chimezie Ogbuji <chimezie@gmail.com>
License: MIT License
Classifier: Development Status :: 4 - Beta
Classifier: Programming Language :: Python
Classifier: Programming Language :: Python :: 3.11
Classifier: Programming Language :: Python :: Implementation :: PyPy
Requires-Python: >=3.10
License-File: LICENSE
Requires-Dist: mlx
Requires-Dist: click
Requires-Dist: tqdm
Requires-Dist: ogbujipt
Requires-Dist: numpy
Requires-Dist: mlx-lm
Requires-Dist: pyyaml
Requires-Dist: pytest
